agentic_astra/__init__.py
agentic_astra/audit.py
agentic_astra/auth.py
agentic_astra/catalog.py
agentic_astra/database.py
agentic_astra/llm.py
agentic_astra/load_tools.py
agentic_astra/logger.py
agentic_astra/run_tool.py
agentic_astra/server.py
agentic_astra/tool_agent.py
agentic_astra/tool_agent_prompt.py
agentic_astra/utils.py
agentic_astra-0.0.5.dist-info/METADATA
agentic_astra-0.0.5.dist-info/WHEEL
agentic_astra-0.0.5.dist-info/entry_points.txt
agentic_astra-0.0.5.dist-info/licenses/LICENSE
agentic_astra-0.0.5.dist-info/RECORD
