Metadata-Version: 2.4
Name: agentic-astra
Version: 0.0.5
Summary: Astra MCP Server
Project-URL: Homepage, https://github.com/smatiolids/agentic-astra
Project-URL: Repository, https://github.com/smatiolids/agentic-astra
Project-URL: Issues, https://github.com/smatiolids/agentic-astra/issues
Author-email: Samuel Matioli <smatioli@gmail.com>, Samuel Matioli <samuel.matioli@ibm.com>
License: MIT License
License-File: LICENSE
Keywords: astra,datastax,mcp,server
Classifier: Development Status :: 3 - Alpha
Classifier: Intended Audience :: Developers
Classifier: License :: OSI Approved :: MIT License
Classifier: Programming Language :: Python :: 3
Classifier: Programming Language :: Python :: 3.12
Requires-Python: >=3.12
Requires-Dist: astrapy>=2.0.1
Requires-Dist: fastmcp>=2.12.1
Requires-Dist: python-dotenv>=1.1.1
Requires-Dist: uvicorn[standard]>=0.30.0
